pynoonlight/__init__.py
pynoonlight/dispatch.py
pynoonlight/py.typed
pynoonlight/tasks.py
pynoonlight-0.4.5.dist-info/LICENSE
pynoonlight-0.4.5.dist-info/METADATA
pynoonlight-0.4.5.dist-info/WHEEL
pynoonlight-0.4.5.dist-info/RECORD
