Metadata-Version: 2.1
Name: pynoonlight
Version: 0.4.5
Summary: Create and update alarms for Noonlight
Home-page: https://IceBotYT.github.io/pynoonlight
License: MIT
Author: IceBotYT
Author-email: icebotyt@outlook.com
Requires-Python: >=3.8,<4.0
Classifier: Development Status :: 4 - Beta
Classifier: Intended Audience :: Developers
Classifier: License :: OSI Approved :: MIT License
Classifier: Operating System :: OS Independent
Classifier: Programming Language :: Python
Classifier: Programming Language :: Python :: 3
Classifier: Programming Language :: Python :: 3.8
Classifier: Programming Language :: Python :: 3.9
Classifier: Programming Language :: Python :: 3.10
Classifier: Programming Language :: Python :: 3.11
Classifier: Programming Language :: Python :: 3.12
Classifier: Programming Language :: Python :: 3.13
Classifier: Topic :: Software Development :: Libraries :: Python Modules
Classifier: Typing :: Typed
Requires-Dist: aiohttp (>=3.8.1,<4.0.0)
Requires-Dist: mkdocstrings-python (>=0.7.1,<0.8.0)
Requires-Dist: pychalk (==2.0.1)
Requires-Dist: pydantic (>=2.10.4,<3.0.0)
Requires-Dist: tenacity (>=8.0.1,<9.0.0)
Requires-Dist: tzlocal (>=4.2,<5.0)
Requires-Dist: validators (>=0.20.0,<0.21.0)
Project-URL: Documentation, https://IceBotYT.github.io/pynoonlight
Project-URL: Repository, https://github.com/IceBotYT/pynoonlight
